enigma/__init__.py
enigma/machine.py
enigma/plugboard.py
enigma/rotor.py
enigma/utils.py
enigma_cipher_machine-0.0.2.dist-info/LICENSE.md
enigma_cipher_machine-0.0.2.dist-info/METADATA
enigma_cipher_machine-0.0.2.dist-info/WHEEL
enigma_cipher_machine-0.0.2.dist-info/top_level.txt
enigma_cipher_machine-0.0.2.dist-info/RECORD
