Metadata-Version: 2.1
Name: enigma-cipher-machine
Version: 0.0.2
Summary: The enigma machine in python
Author-email: Raymas <IgnaceCousteau@protonmail.com>
Project-URL: Homepage, https://github.com/raymas/enigma-machine
Project-URL: Bug Tracker, https://github.com/raymas/enigma-machine/issues
Classifier: Programming Language :: Python :: 3
Classifier: License :: OSI Approved :: MIT License
Classifier: Operating System :: OS Independent
Requires-Python: >=3.7
License-File: LICENSE.md
